mcnbt/__init__.py
mcnbt/nbt.py
mcnbt/factory_tags/__init__.py
mcnbt/factory_tags/base_builder.py
mcnbt/factory_tags/base_builder_parent.py
mcnbt/factory_tags/base_builder_value.py
mcnbt/factory_tags/builder_byte.py
mcnbt/factory_tags/builder_byte_array.py
mcnbt/factory_tags/builder_compound.py
mcnbt/factory_tags/builder_double.py
mcnbt/factory_tags/builder_float.py
mcnbt/factory_tags/builder_int.py
mcnbt/factory_tags/builder_int_array.py
mcnbt/factory_tags/builder_list.py
mcnbt/factory_tags/builder_long.py
mcnbt/factory_tags/builder_long_array.py
mcnbt/factory_tags/builder_short.py
mcnbt/factory_tags/builder_string.py
mcnbt/factory_tags/tags/__init__.py
mcnbt/factory_tags/tags/tag_byte.py
mcnbt/factory_tags/tags/tag_byte_array.py
mcnbt/factory_tags/tags/tag_compound.py
mcnbt/factory_tags/tags/tag_double.py
mcnbt/factory_tags/tags/tag_float.py
mcnbt/factory_tags/tags/tag_int.py
mcnbt/factory_tags/tags/tag_int_array.py
mcnbt/factory_tags/tags/tag_list.py
mcnbt/factory_tags/tags/tag_long.py
mcnbt/factory_tags/tags/tag_long_array.py
mcnbt/factory_tags/tags/tag_short.py
mcnbt/factory_tags/tags/tag_string.py
mcnbt/factory_tags/tags/base_tags/__init__.py
mcnbt/factory_tags/tags/base_tags/base.py
mcnbt/factory_tags/tags/base_tags/baseParent.py
mcnbt/factory_tags/tags/base_tags/baseValue.py
mcnbt-0.0.2.dist-info/METADATA
mcnbt-0.0.2.dist-info/WHEEL
mcnbt-0.0.2.dist-info/licenses/LICENSE
mcnbt-0.0.2.dist-info/RECORD
