Metadata-Version: 2.3
Name: mcnbt
Version: 0.0.2
Summary: A lightweight library for reading, editing, and saving Minecraft NBT files.
Project-URL: Homepage, https://github.com/NKvinibrian/McNBTReader
Project-URL: Issues, https://github.com/NKvinibrian/McNBTReader/issues
Author-email: Vinicius Wiggers <vi_ni_wiggers@hotmail.com>
License-File: LICENSE
Classifier: Intended Audience :: Developers
Classifier: License :: OSI Approved :: MIT License
Classifier: Operating System :: OS Independent
Classifier: Programming Language :: Python :: 3
Classifier: Topic :: Games/Entertainment
Classifier: Topic :: Software Development :: Libraries :: Python Modules
Requires-Python: >=3.8
